sphinx_performance/__init__.py
sphinx_performance/analysis.py
sphinx_performance/call.py
sphinx_performance/config.py
sphinx_performance/performance.py
sphinx_performance/projectenv.py
sphinx_performance/projects/basic/_static/README
sphinx_performance/projects/basic/conf.template
sphinx_performance/projects/basic/index.template
sphinx_performance/projects/basic/page.template
sphinx_performance/projects/basic/performance.py
sphinx_performance/projects/basic/requirements.template
sphinx_performance/projects/needs/_static/README
sphinx_performance/projects/needs/conf.template
sphinx_performance/projects/needs/index.template
sphinx_performance/projects/needs/page.template
sphinx_performance/projects/needs/performance.py
sphinx_performance/projects/needs/requirements.template
sphinx_performance/projects/theme/_static/README
sphinx_performance/projects/theme/conf.template
sphinx_performance/projects/theme/index.template
sphinx_performance/projects/theme/page.template
sphinx_performance/projects/theme/performance.py
sphinx_performance/projects/theme/requirements.template
sphinx_performance/utils.py
sphinx_performance-0.1.7.dist-info/entry_points.txt
sphinx_performance-0.1.7.dist-info/LICENSE
sphinx_performance-0.1.7.dist-info/WHEEL
sphinx_performance-0.1.7.dist-info/METADATA
sphinx_performance-0.1.7.dist-info/RECORD
