Metadata-Version: 2.1
Name: sphinx-performance
Version: 0.1.7
Summary: 
Home-page: https://github.com/useblocks/sphinx-performance
License: MIT
Author: team useblocks
Requires-Python: >=3.7.0,<4.0.0
Classifier: Development Status :: 5 - Production/Stable
Classifier: Framework :: Sphinx
Classifier: Intended Audience :: Developers
Classifier: License :: OSI Approved :: MIT License
Classifier: Operating System :: OS Independent
Classifier: Programming Language :: Python
Classifier: Programming Language :: Python :: 3
Classifier: Programming Language :: Python :: 3.7
Classifier: Programming Language :: Python :: 3.8
Classifier: Programming Language :: Python :: 3.9
Classifier: Programming Language :: Python :: 3.10
Classifier: Programming Language :: Python :: 3
Classifier: Programming Language :: Python :: 3.10
Classifier: Programming Language :: Python :: 3.11
Classifier: Programming Language :: Python :: 3.7
Classifier: Programming Language :: Python :: 3.8
Classifier: Programming Language :: Python :: 3.9
Classifier: Topic :: Documentation
Classifier: Topic :: Utilities
Provides-Extra: docs
Requires-Dist: Jinja2 (>=3.0.3,<4.0.0)
Requires-Dist: click (>=8.0.3,<9.0.0)
Requires-Dist: memray (>=1.3.1,<2.0.0)
Requires-Dist: rich (>=11.2.0,<12.0.0)
Project-URL: Documentation, https://sphinx-performance.readthedocs.io/en/latest/
Project-URL: Repository, https://github.com/useblocks/sphinx-performance
